maxentsolver/__init__.py
maxentsolver/models/__init__.py
maxentsolver/models/generative.py
maxentsolver/models/maxent.py
maxentsolver/models/mcmc.py
maxentsolver/models/meanfield.py
maxentsolver/models/nodewisepl.py
maxentsolver/models/pseudolikelihood.py
maxentsolver/utils/__init__.py
maxentsolver/utils/plotting.py
maxentsolver/utils/preprocess.py
maxentsolver-0.2.5.dist-info/METADATA
maxentsolver-0.2.5.dist-info/WHEEL
maxentsolver-0.2.5.dist-info/licenses/LICENSE
maxentsolver-0.2.5.dist-info/RECORD
